sort_merge/__init__.py
sort_merge/mergesort.py
sort_merge-0.0.1.dist-info/LICENSE
sort_merge-0.0.1.dist-info/METADATA
sort_merge-0.0.1.dist-info/WHEEL
sort_merge-0.0.1.dist-info/top_level.txt
sort_merge-0.0.1.dist-info/RECORD
